slackme.py
slackme-1.0.0.dist-info/DESCRIPTION.rst
slackme-1.0.0.dist-info/LICENSE.txt
slackme-1.0.0.dist-info/METADATA
slackme-1.0.0.dist-info/RECORD
slackme-1.0.0.dist-info/WHEEL
slackme-1.0.0.dist-info/entry_points.txt
slackme-1.0.0.dist-info/metadata.json
slackme-1.0.0.dist-info/top_level.txt
